examples/__init__.py
flask_loguru/__init__.py
flask_loguru/__version__.py
flask_loguru/compress.py
flask_loguru/macro.py
tests/__init__.py
tests/conftest.py
tests/test_log.py
tests/test_rotate.py
flask_loguru-1.0.0.dist-info/METADATA
flask_loguru-1.0.0.dist-info/WHEEL
flask_loguru-1.0.0.dist-info/top_level.txt
flask_loguru-1.0.0.dist-info/RECORD
