Metadata-Version: 2.1
Name: flask-loguru
Version: 1.0.0
Summary: Flask extension of loguru
Home-page: https://github.com/Eastwu5788/Flask-Loguru
Author: LeonardWoo
Author-email: wudong@eastwu.cn
License: MIT
Platform: UNKNOWN
Classifier: License :: OSI Approved :: MIT License
Classifier: Programming Language :: Python
Classifier: Programming Language :: Python :: 3
Classifier: Programming Language :: Python :: 3.6
Classifier: Programming Language :: Python :: Implementation :: CPython
Classifier: Programming Language :: Python :: Implementation :: PyPy
Requires-Python: >=3.6.0
Requires-Dist: loguru
